rankers/__init__.py
rankers/_optional.py
rankers/_util.py
rankers/datasets/__init__.py
rankers/datasets/corpus.py
rankers/datasets/dataset.py
rankers/datasets/flaxloader.py
rankers/datasets/loader.py
rankers/modelling/__init__.py
rankers/modelling/base.py
rankers/modelling/bge/__init__.py
rankers/modelling/bge/bge.py
rankers/modelling/cat/__init__.py
rankers/modelling/cat/cat.py
rankers/modelling/cat/flaxcat.py
rankers/modelling/dot/__init__.py
rankers/modelling/dot/dot.py
rankers/modelling/dot/flaxdot.py
rankers/modelling/seq2seq/__init__.py
rankers/modelling/seq2seq/flaxseq2seq.py
rankers/modelling/seq2seq/seq2seq.py
rankers/modelling/sparse/__init__.py
rankers/modelling/sparse/flaxsparse.py
rankers/modelling/sparse/sparse.py
rankers/pyterrier/__init__.py
rankers/pyterrier/cat/__init__.py
rankers/pyterrier/cat/cat.py
rankers/pyterrier/cat/flaxcat.py
rankers/pyterrier/dot/__init__.py
rankers/pyterrier/dot/dot.py
rankers/pyterrier/dot/flaxdot.py
rankers/pyterrier/seq2seq/__init__.py
rankers/pyterrier/seq2seq/seq2seq.py
rankers/pyterrier/sparse/__init__.py
rankers/pyterrier/sparse/sparse.py
rankers/train/__init__.py
rankers/train/data_arguments.py
rankers/train/model_arguments.py
rankers/train/trainer.py
rankers/train/training_arguments.py
rankers/train/loss/__init__.py
rankers/train/loss/util.py
rankers/train/loss/flax/__init__.py
rankers/train/loss/flax/listwise.py
rankers/train/loss/flax/pairwise.py
rankers/train/loss/flax/pointwise.py
rankers/train/loss/torch/__init__.py
rankers/train/loss/torch/listwise.py
rankers/train/loss/torch/pairwise.py
rankers/train/loss/torch/pointwise.py
rankers-0.0.6.dist-info/LICENSE
rankers-0.0.6.dist-info/METADATA
rankers-0.0.6.dist-info/WHEEL
rankers-0.0.6.dist-info/top_level.txt
rankers-0.0.6.dist-info/RECORD
