Metadata-Version: 2.1
Name: rankers
Version: 0.0.6
Summary: A package for training and evaluating neural rankers.
Author: Andrew Parry
Author-email: Andrew Parry <0andrewparry@gmail.com>
Maintainer-email: Andrew Parry <0andrewparry@gmail.com>
License:                                  Apache License
Project-URL: Repository, https://github.com/Parry-Parry/rankers.git
Keywords: pytorch,transformers,ranking,information retrieval
Classifier: Programming Language :: Python
Classifier: License :: OSI Approved :: Apache Software License
Classifier: Operating System :: OS Independent
Classifier: Development Status :: 3 - Alpha
Classifier: Intended Audience :: Developers
Classifier: Intended Audience :: Science/Research
Classifier: Topic :: Scientific/Engineering :: Artificial Intelligence
Requires-Python: >=3.10
License-File: LICENSE
Requires-Dist: torch
Requires-Dist: transformers
Requires-Dist: datasets
Requires-Dist: ir-measures
Requires-Dist: pandas
Requires-Dist: more_itertools
